tensortracker-0.1.0.dist-info/METADATA
tensortracker-0.1.0.dist-info/WHEEL
tensortracker-0.1.0.dist-info/licenses/LICENSE
tensortracker/__init__.py
tensortracker/tensortracker.cp312-win32.pyd
tensortracker-0.1.0.dist-info/RECORD
