Metadata-Version: 2.4
Name: tensortracker
Version: 0.1.0
Classifier: Programming Language :: Python :: 3
Classifier: Programming Language :: Python :: 3.8
Classifier: Programming Language :: Python :: 3.9
Classifier: Programming Language :: Python :: 3.10
Classifier: Programming Language :: Python :: 3.11
Classifier: Programming Language :: Rust
Classifier: Development Status :: 3 - Alpha
Classifier: Intended Audience :: Science/Research
Classifier: Topic :: Scientific/Engineering :: Artificial Intelligence
Requires-Dist: matplotlib>=3.7.5
Requires-Dist: maturin>=1.9.2
Requires-Dist: pandas>=2.0.3
Requires-Dist: pytest>=8.3.5
Requires-Dist: safetensors>=0.5.3
Requires-Dist: torchvision>=0.20.1
License-File: LICENSE
Summary: Diff and patch safetensors models
Requires-Python: >=3.8
